altunityrunnerfc/__init__.py
altunityrunnerfc/altElement.py
altunityrunnerfc/altUnityExceptions.py
altunityrunnerfc/by.py
altunityrunnerfc/player_pref_key_type.py
altunityrunnerfc/runner.py
altunityrunnerfc/commands/__init__.py
altunityrunnerfc/commands/base_command.py
altunityrunnerfc/commands/close_connection.py
altunityrunnerfc/commands/command_returning_alt_elements.py
altunityrunnerfc/commands/enable_logging.py
altunityrunnerfc/commands/get_png_screenshot.py
altunityrunnerfc/commands/FindObjects/__init__.py
altunityrunnerfc/commands/FindObjects/find_chui_button_by_name_in_list.py
altunityrunnerfc/commands/FindObjects/find_object.py
altunityrunnerfc/commands/FindObjects/find_object_which_contains.py
altunityrunnerfc/commands/FindObjects/find_objects.py
altunityrunnerfc/commands/FindObjects/find_objects_which_contains.py
altunityrunnerfc/commands/FindObjects/get_all_elements.py
altunityrunnerfc/commands/FindObjects/wait_for_object.py
altunityrunnerfc/commands/FindObjects/wait_for_object_to_not_be_present.py
altunityrunnerfc/commands/FindObjects/wait_for_object_which_contains.py
altunityrunnerfc/commands/FindObjects/wait_for_object_with_text.py
altunityrunnerfc/commands/InputActions/__init__.py
altunityrunnerfc/commands/InputActions/move_mouse.py
altunityrunnerfc/commands/InputActions/move_mouse_and_wait.py
altunityrunnerfc/commands/InputActions/press_key.py
altunityrunnerfc/commands/InputActions/press_key_and_wait.py
altunityrunnerfc/commands/InputActions/scroll_mouse.py
altunityrunnerfc/commands/InputActions/scroll_mouse_and_wait.py
altunityrunnerfc/commands/InputActions/swipe.py
altunityrunnerfc/commands/InputActions/swipe_and_wait.py
altunityrunnerfc/commands/InputActions/tap_at_coordinates.py
altunityrunnerfc/commands/InputActions/tilt.py
altunityrunnerfc/commands/ObjectCommands/__init__.py
altunityrunnerfc/commands/ObjectCommands/call_component_method.py
altunityrunnerfc/commands/ObjectCommands/call_static_methods.py
altunityrunnerfc-1.5.2.8.dist-info/METADATA
altunityrunnerfc-1.5.2.8.dist-info/WHEEL
altunityrunnerfc-1.5.2.8.dist-info/top_level.txt
altunityrunnerfc-1.5.2.8.dist-info/RECORD
