Metadata-Version: 2.1
Name: altunityrunnerfc
Version: 1.5.2.8
Summary: Alt Unity Runner with Fishing Clash compatibility
Home-page: https://gitlab.com/piotrrudnicki/altunityrunner-fc
Author: AltUnityRunner - Altom. FC Modifications - Piotr Rudnicki
Author-email: piotr.rudnicki@tensquaregames.com
License: opensource
Platform: UNKNOWN
